cellmaps_imagedownloader/__init__.py
cellmaps_imagedownloader/cellmaps_imagedownloadercmd.py
cellmaps_imagedownloader/exceptions.py
cellmaps_imagedownloader/gene.py
cellmaps_imagedownloader/proteinatlas.py
cellmaps_imagedownloader/readme_outputs.txt
cellmaps_imagedownloader/runner.py
cellmaps_imagedownloader-0.3.0.data/scripts/cellmaps_imagedownloadercmd.py
cellmaps_imagedownloader-0.3.0.dist-info/licenses/AUTHORS.rst
cellmaps_imagedownloader-0.3.0.dist-info/licenses/LICENSE
cellmaps_imagedownloader-0.3.0.dist-info/METADATA
cellmaps_imagedownloader-0.3.0.dist-info/WHEEL
cellmaps_imagedownloader-0.3.0.dist-info/top_level.txt
cellmaps_imagedownloader-0.3.0.dist-info/RECORD
