Metadata-Version: 2.4
Name: cellmaps_imagedownloader
Version: 0.3.0
Summary: A tool to download specified image data from the Human Protein Atlas website using CSV file or to copy data from CM4AI dataset
Home-page: https://github.com/idekerlab/cellmaps_imagedownloader
Author: Cell Maps team
Author-email: tools@cm4ai.org
License: MIT license
Keywords: cellmaps_imagedownloader
Classifier: Development Status :: 2 - Pre-Alpha
Classifier: Intended Audience :: Developers
Classifier: License :: OSI Approved :: MIT License
Classifier: Natural Language :: English
Classifier: Programming Language :: Python :: 3.8
Classifier: Programming Language :: Python :: 3.9
Classifier: Programming Language :: Python :: 3.10
Classifier: Programming Language :: Python :: 3.11
License-File: LICENSE
License-File: AUTHORS.rst
Requires-Dist: cellmaps_utils<1.0.0,>=0.4.0
Requires-Dist: requests<3.0.0,>=2.32.3
Requires-Dist: mygene<4.0.0,>=3.2.2
Requires-Dist: pandas<3.0.0,>=2.0.0
Requires-Dist: tqdm<5.0.0,>=4.67.1
Dynamic: author
Dynamic: author-email
Dynamic: classifier
Dynamic: description
Dynamic: description-content-type
Dynamic: home-page
Dynamic: keywords
Dynamic: license
Dynamic: license-file
Dynamic: requires-dist
Dynamic: summary
